joblib_modal/__init__.py
joblib_modal/_modal.py
joblib_modal-0.1.1.dist-info/METADATA
joblib_modal-0.1.1.dist-info/WHEEL
joblib_modal-0.1.1.dist-info/licenses/LICENSE
joblib_modal-0.1.1.dist-info/RECORD
