Metadata-Version: 2.4
Name: joblib_modal
Version: 0.1.1
Summary: A Modal backend for Joblib
Author-email: Adrin Jalali <adrin.jalali@gmail.com>
License: BSD 3-Clause License
License-File: LICENSE
Requires-Python: >=3.10
Requires-Dist: joblib
Requires-Dist: modal
